mcnn/__init__.py
mcnn/make.py
mcnn-1.1.2.dist-info/LICENSE.md
mcnn-1.1.2.dist-info/METADATA
mcnn-1.1.2.dist-info/WHEEL
mcnn-1.1.2.dist-info/top_level.txt
mcnn-1.1.2.dist-info/RECORD
