Metadata-Version: 2.1
Name: mcnn
Version: 1.1.2
Summary: MakeCNN is how we make sure everybody can benefit from ML.
Home-page: https://github.com/anish-lakkapragada/MakeCNN
Author: Anish Lakkapragada
Author-email: anish.lakkapragada@gmail.com
License: new BSD
Download-URL: https://github.com/anish-lakkapragada/MakeCNN/archive/refs/tags/1.0.4.tar.gz
Project-URL: Source Code, https://github.com/anish-lakkapragada/MakeCNN
Keywords: Machine Learning,Deep Learning,CNN
Platform: UNKNOWN
Classifier: Development Status :: 5 - Production/Stable
Classifier: Programming Language :: Python :: 3
Classifier: Programming Language :: Python :: 3.8
Classifier: Programming Language :: Python :: 3.9
Classifier: Intended Audience :: Developers
Classifier: Topic :: Software Development :: Build Tools
Classifier: Programming Language :: Python :: 3
Requires-Python: >=3
Requires-Dist: numpy
Requires-Dist: opencv-python
Requires-Dist: tensorflow
